perplexed/__init__.py
perplexed/_modidx.py
perplexed/core.py
perplexed-0.0.1.dist-info/LICENSE
perplexed-0.0.1.dist-info/METADATA
perplexed-0.0.1.dist-info/WHEEL
perplexed-0.0.1.dist-info/entry_points.txt
perplexed-0.0.1.dist-info/top_level.txt
perplexed-0.0.1.dist-info/RECORD
