Metadata-Version: 2.1
Name: perplexed
Version: 0.0.1
Summary: Find out where your model is perplexed!
Home-page: https://github.com/ncoop57/perplexed
Author: ncoop57
Author-email: nacooper01@wm.edu
License: Apache Software License 2.0
Keywords: nbdev jupyter notebook python
Classifier: Development Status :: 4 - Beta
Classifier: Intended Audience :: Developers
Classifier: Natural Language :: English
Classifier: Programming Language :: Python :: 3.7
Classifier: Programming Language :: Python :: 3.8
Classifier: Programming Language :: Python :: 3.9
Classifier: Programming Language :: Python :: 3.10
Classifier: License :: OSI Approved :: Apache Software License
Requires-Python: >=3.7
License-File: LICENSE
Requires-Dist: datasets
Requires-Dist: fastcore
Requires-Dist: rich
Requires-Dist: torch
Requires-Dist: transformers
Provides-Extra: dev
Requires-Dist: code-tokenizers ; extra == 'dev'
Requires-Dist: ipywidgets ; extra == 'dev'
Requires-Dist: matplotlib ; extra == 'dev'
Requires-Dist: nbdev ; extra == 'dev'
Requires-Dist: seaborn ; extra == 'dev'
Requires-Dist: twine ; extra == 'dev'
